{
  "w22ptsdvs2": {
    "address": "Kampung Kanchong Tengah, Banting, Selangor, Malaysia 42700",
    "createdAt": "2018-09-09T15:44:09+08:00",
    "location": {
      "latitude": 2.750275,
      "longitude": 101.495666
    },
    "name": "MASJID AN NUR",
    "type": "Mosque",
    "updatedAt": "2018-09-09T15:44:09+08:00",
    "uuid": "16017ff3-7423-42b5-9bf2-afc9dbd149e8",
    "geohash": "w22ptsdvs2",
    "remarks": "Sejarah solat jumaat pertama dikampong ini ialah pada 12/12/1972 disebuah surau. Kemudiannya suaru tersebut telah diubahsuai menjadi maasjid dan siap dibina pada tahun 1982. Masjid ini telah disempurnakan oleh YBhg Ustaz Zainal Hj Ariffin, penyelia Masjid Kuala Langat. .",
    "source_musolla_id": "MY-10-KL-00224",
    "provision": "Antara kemudahan yang terdapat ialah  ruang parkir yang luas,alat penghawa dingin,   van jenazah dan urusan jenazah dan  ruangan solat yang luas.",
    "directions": "Masjid ini terletak dikawasan perkampongan Kampong Kanchong Tengah."
  }
}