{
  "w22wefgyyh": {
    "address": "Jalan Seremban-Tampin, 71300 Bongek, Negeri Sembilan, Malaysia 71300",
    "contact": "012-6315075",
    "createdAt": "2018-09-09T15:44:09+08:00",
    "location": {
      "latitude": 2.565115,
      "longitude": 102.123336
    },
    "name": "MASJID KARIAH BONGEK",
    "type": "Mosque",
    "updatedAt": "2018-09-09T15:44:09+08:00",
    "uuid": "6ad720a4-c3ef-42d7-b9ca-f160383e2187",
    "geohash": "w22wefgyyh",
    "remarks": "Masjid Kariah Bongek telah dibina pada tahun 1901M. Pengasasnya ialah penduduk setempat yang juga telah mewakafkan tanahnya untuk tapak masjid ini.\n\nApabila seorang ahli kariah telah bermurah hati dengan mewakafkan tanahnya bagi tujuan pembangunan masjid baru maka pada tahun 1967M Kerajaan Negeri telah memberikan bantuan membina sebuah masjid baru yang masih digunakan sehingga kini.\n\nMasjd ini pernah dibaiki dan dibesarkan pada tahun 1967M, 2004M dan 2005M. Semasa dibina masjid ini mempunyai kapasiti jemaah seramai 50 orang sahaja dan kini jumlah tersebut telah meningkat kepada 200 orang jemaah dalam satu - satu masa.",
    "source_musolla_id": "MY-05-RB-00106",
    "provision": "1.\tRuang solat lelaki dan wanita\n2.\tTempat wudhuk\n3.\tTandas\n4.\tBilik Stor\n5.\tRuang pengurusan jenazah \n6.\tRuang makan jemaah      \n7.\tParking kereta dan motosikal  \n8.\tTempat istirehat"
  }
}