{
  "w2838jv6n9": {
    "address": "SS 4A, Petaling Jaya, Selangor, Malaysia 47301",
    "createdAt": "2018-09-09T15:44:09+08:00",
    "location": {
      "latitude": 3.10811,
      "longitude": 101.609053
    },
    "name": "MASJID AL - EHSAN",
    "type": "Mosque",
    "updatedAt": "2018-09-09T15:44:09+08:00",
    "uuid": "aec8bdc3-56d3-4e57-aedf-29101a74bc85",
    "geohash": "w2838jv6n9",
    "remarks": "Pada asalnya,ia hanya adalah sebuah surau yang dibina dari papan.Kemudian ianya berpindah ke tempat baru untuk dibina masjid. Masjid ini telah dibina hasil dari sumbangan kerajaan negeri dan sumbangan orang ramai. Pembinaannya bermula pada 1984 dan telah siap digunakan pada tahun 1986. Bersesuaian dengan keperluan semasa maka ianya telah dinaiktaraf untuk dijadikan masjid untuk solat jumaat pada tahun 2002.",
    "source_musolla_id": "MY-10-PTG-00274",
    "provision": "Kemudahan yang terdapat di masjid ini ialah bilik serbaguna,bilik imam,perpustakaan, CCTV,ruang makan dan computer. Ruang solatnya dilengkapi alat penghawa dingin untuk keselesaan pengunjungnya."
  }
}