{
  "w309326fu5": {
    "address": "FELDA Kemahang 1, Jedok, Kelantan, Malaysia 17510",
    "createdAt": "2018-09-09T15:44:09+08:00",
    "location": {
      "latitude": 5.846591,
      "longitude": 102.012013
    },
    "name": "MASJID MUKIM KEMAHANG 1",
    "type": "Mosque",
    "updatedAt": "2018-09-09T15:44:09+08:00",
    "uuid": "792b59a9-46e4-4b75-8c3b-9694f47ad60f",
    "geohash": "w309326fu5",
    "remarks": "Masjid mukim kemahang 1 sekarang ini dalam proses pembinaan di bahagian ruang solat utama secara menyeluruh dan proses pembinaan ini dijangka siap pada pertengahan tahun 2012.",
    "source_musolla_id": "MY-03-TM-00336",
    "provision": "Diantara kemudahan-kemudahan yang terdapat di masjid ini adalah stor,pejabat,bilik imam,tandas,tempat wuduk bagi lelaki dan perempuan.\nParking terbuka yang mana boleh menempatkan lebih 20 buah kenderaan dalam satu masa."
  }
}