{
  "w30fbcnet0": {
    "address": "Kampung Wakaf Zin, Tawang, Kelantan, Malaysia 16320",
    "createdAt": "2018-09-09T15:44:09+08:00",
    "location": {
      "latitude": 6.114494,
      "longitude": 102.346798
    },
    "name": "MASJID MUKIM SESENAK",
    "type": "Mosque",
    "updatedAt": "2018-09-09T15:44:09+08:00",
    "uuid": "c3c66aa7-07a8-48b4-847e-38bddbbc5c56",
    "geohash": "w30fbcnet0",
    "remarks": "Masjid dibina pada tahun 1960 dan pernah dirasmikan oleh Tengku Tan Sri Ghazali Hamzah yang pada ketika itu beliau adalah Menteri Kewangan Mlalaysia. Masjid ini dibina diatas tanah orang yang diwakafkan untuk membina masjid. Pada asalnya masjid ialah sebuah surau dan telah dinaiktaraf menjadi sebuah masjid. Pengasas masjid ini adalah Tengku Razaleigh",
    "source_musolla_id": "MY-03-BCK-00478",
    "provision": "Masjid ini menyediakan kemudahan tandas serta tempat berwuduk  lelaki dan perempuan untuk kemudahan pengunjung masjid.Selain itu, masjid ini mempunyai keranda serta tempat mandi mayat supaya pengurusan jenazah dapat dilakukan.",
    "directions": "Lokasi masjid terletak di sebuah kampung dan masjid hanya 20km dari Bandar Bachok"
  }
}